tableau_api_lib/__init__.py
tableau_api_lib/tableau_server_connection.py
tableau_api_lib/api_endpoints/__init__.py
tableau_api_lib/api_endpoints/auth_endpoint.py
tableau_api_lib/api_endpoints/base_endpoint.py
tableau_api_lib/api_endpoints/column_endpoint.py
tableau_api_lib/api_endpoints/data_alert_endpoint.py
tableau_api_lib/api_endpoints/database_endpoint.py
tableau_api_lib/api_endpoints/datasource_endpoint.py
tableau_api_lib/api_endpoints/dqwarning_endpoint.py
tableau_api_lib/api_endpoints/encryption_endpoint.py
tableau_api_lib/api_endpoints/favorites_endpoint.py
tableau_api_lib/api_endpoints/file_upload_endpoint.py
tableau_api_lib/api_endpoints/flow_endpoint.py
tableau_api_lib/api_endpoints/flow_run_endpoint.py
tableau_api_lib/api_endpoints/graphql_endpoint.py
tableau_api_lib/api_endpoints/group_endpoint.py
tableau_api_lib/api_endpoints/jobs_endpoint.py
tableau_api_lib/api_endpoints/permissions_endpoint.py
tableau_api_lib/api_endpoints/project_endpoint.py
tableau_api_lib/api_endpoints/schedules_endpoint.py
tableau_api_lib/api_endpoints/site_endpoint.py
tableau_api_lib/api_endpoints/subscriptions_endpoint.py
tableau_api_lib/api_endpoints/table_endpoint.py
tableau_api_lib/api_endpoints/tasks_endpoint.py
tableau_api_lib/api_endpoints/user_endpoint.py
tableau_api_lib/api_endpoints/view_endpoint.py
tableau_api_lib/api_endpoints/webhook_endpoint.py
tableau_api_lib/api_endpoints/workbook_endpoint.py
tableau_api_lib/api_requests/__init__.py
tableau_api_lib/api_requests/add_datasource_permissions_request.py
tableau_api_lib/api_requests/add_datasource_to_favorites_request.py
tableau_api_lib/api_requests/add_datasource_to_schedule_request.py
tableau_api_lib/api_requests/add_default_permissions_request.py
tableau_api_lib/api_requests/add_dqwarning_request.py
tableau_api_lib/api_requests/add_flow_permissions_request.py
tableau_api_lib/api_requests/add_flow_to_schedule_request.py
tableau_api_lib/api_requests/add_project_permissions_request.py
tableau_api_lib-0.1.49.dist-info/LICENSE
tableau_api_lib-0.1.49.dist-info/METADATA
tableau_api_lib-0.1.49.dist-info/WHEEL
tableau_api_lib-0.1.49.dist-info/top_level.txt
tableau_api_lib-0.1.49.dist-info/RECORD
